kociemba/__init__.py
kociemba/build_ckociemba.py
kociemba/ckociembawrapper.pyd
kociemba/command_line.py
kociemba/ckociemba/coordcube.c
kociemba/ckociemba/cubiecube.c
kociemba/ckociemba/facecube.c
kociemba/ckociemba/prunetable_helpers.c
kociemba/ckociemba/search.c
kociemba/ckociemba/solve.c
kociemba/ckociemba/include/color.h
kociemba/ckociemba/include/coordcube.h
kociemba/ckociemba/include/corner.h
kociemba/ckociemba/include/cubiecube.h
kociemba/ckociemba/include/edge.h
kociemba/ckociemba/include/facecube.h
kociemba/ckociemba/include/facelet.h
kociemba/ckociemba/include/prunetable_helpers.h
kociemba/ckociemba/include/search.h
kociemba/cprunetables/FRtoBR_Move
kociemba/cprunetables/MergeURtoULandUBtoDF
kociemba/cprunetables/Slice_Flip_Prun
kociemba/cprunetables/Slice_Twist_Prun
kociemba/cprunetables/Slice_URFtoDLF_Parity_Prun
kociemba/cprunetables/Slice_URtoDF_Parity_Prun
kociemba/cprunetables/UBtoDF_Move
kociemba/cprunetables/URFtoDLF_Move
kociemba/cprunetables/URtoDF_Move
kociemba/cprunetables/URtoUL_Move
kociemba/cprunetables/flipMove
kociemba/cprunetables/twistMove
kociemba/pykociemba/__init__.py
kociemba/pykociemba/color.py
kociemba/pykociemba/coordcube.py
kociemba/pykociemba/corner.py
kociemba/pykociemba/cubiecube.py
kociemba/pykociemba/edge.py
kociemba/pykociemba/facecube.py
kociemba/pykociemba/facelet.py
kociemba/pykociemba/search.py
kociemba/pykociemba/tools.py
kociemba/pykociemba/prunetables/FRtoBR_Move.pkl
kociemba/pykociemba/prunetables/MergeURtoULandUBtoDF.pkl
kociemba/pykociemba/prunetables/Slice_Flip_Prun.pkl
kociemba/pykociemba/prunetables/Slice_Twist_Prun.pkl
kociemba/pykociemba/prunetables/Slice_URFtoDLF_Parity_Prun.pkl
kociemba/pykociemba/prunetables/Slice_URtoDF_Parity_Prun.pkl
kociemba/pykociemba/prunetables/UBtoDF_Move.pkl
kociemba/pykociemba/prunetables/URFtoDLF_Move.pkl
kociemba/pykociemba/prunetables/URtoDF_Move.pkl
kociemba/pykociemba/prunetables/URtoUL_Move.pkl
kociemba-1.2.dist-info/DESCRIPTION.rst
kociemba-1.2.dist-info/METADATA
kociemba-1.2.dist-info/RECORD
kociemba-1.2.dist-info/WHEEL
kociemba-1.2.dist-info/entry_points.txt
kociemba-1.2.dist-info/metadata.json
kociemba-1.2.dist-info/top_level.txt
