Metadata-Version: 2.0
Name: kociemba
Version: 1.2
Summary: Python/C implementation of Herbert Kociemba's Two-Phase algorithm for solving Rubik's Cube
Home-page: https://github.com/muodov/kociemba
Author: muodov
Author-email: muodov@gmail.com
License: GPLv2
Keywords: kociemba rubik cube solver twophase
Platform: UNKNOWN
Classifier: Development Status :: 5 - Production/Stable
Classifier: Programming Language :: Python
Requires-Dist: cffi (>=1.0.0)
Requires-Dist: future
